uproot3/__init__.py
uproot3/_help.py
uproot3/_util.py
uproot3/cache.py
uproot3/const.py
uproot3/pandas.py
uproot3/rootio.py
uproot3/tree.py
uproot3/version.py
uproot3/_connect/__init__.py
uproot3/_connect/_pandas.py
uproot3/interp/__init__.py
uproot3/interp/auto.py
uproot3/interp/interp.py
uproot3/interp/jagged.py
uproot3/interp/numerical.py
uproot3/interp/objects.py
uproot3/source/__init__.py
uproot3/source/chunked.py
uproot3/source/compressed.py
uproot3/source/cursor.py
uproot3/source/file.py
uproot3/source/http.py
uproot3/source/memmap.py
uproot3/source/source.py
uproot3/source/xrootd.py
uproot3/write/TDirectory.py
uproot3/write/TFile.py
uproot3/write/TFree.py
uproot3/write/TKey.py
uproot3/write/__init__.py
uproot3/write/compress.py
uproot3/write/streamers.py
uproot3/write/util.py
uproot3/write/objects/TH.py
uproot3/write/objects/TObjString.py
uproot3/write/objects/TTree.py
uproot3/write/objects/__init__.py
uproot3/write/objects/util.py
uproot3/write/sink/__init__.py
uproot3/write/sink/cursor.py
uproot3/write/sink/file.py
uproot3-3.14.4.dist-info/LICENSE
uproot3-3.14.4.dist-info/METADATA
uproot3-3.14.4.dist-info/WHEEL
uproot3-3.14.4.dist-info/top_level.txt
uproot3-3.14.4.dist-info/RECORD
