Metadata-Version: 2.1
Name: uproot3
Version: 3.14.4
Summary: ROOT I/O in pure Python and Numpy.
Home-page: https://github.com/scikit-hep/uproot3
Author: Jim Pivarski (IRIS-HEP)
Author-email: pivarski@princeton.edu
Maintainer: Jim Pivarski (IRIS-HEP)
Maintainer-email: pivarski@princeton.edu
License: BSD 3-clause
Download-URL: https://github.com/scikit-hep/uproot3/releases
Platform: Any
Classifier: Development Status :: 7 - Inactive
Classifier: Intended Audience :: Developers
Classifier: Intended Audience :: Information Technology
Classifier: Intended Audience :: Science/Research
Classifier: License :: OSI Approved :: BSD License
Classifier: Operating System :: MacOS
Classifier: Operating System :: POSIX
Classifier: Operating System :: Unix
Classifier: Programming Language :: Python
Classifier: Programming Language :: Python :: 2.7
Classifier: Programming Language :: Python :: 3.5
Classifier: Programming Language :: Python :: 3.6
Classifier: Programming Language :: Python :: 3.7
Classifier: Programming Language :: Python :: 3.8
Classifier: Programming Language :: Python :: 3.9
Classifier: Topic :: Scientific/Engineering
Classifier: Topic :: Scientific/Engineering :: Information Analysis
Classifier: Topic :: Scientific/Engineering :: Mathematics
Classifier: Topic :: Scientific/Engineering :: Physics
Classifier: Topic :: Software Development
Classifier: Topic :: Utilities
Requires-Python: >=2.7, !=3.0.*, !=3.1.*, !=3.2.*, !=3.3.*, !=3.4.*
Provides-Extra: testing
Provides-Extra: compress
